.gitignore
README.md
customize.py
pyproject.toml
requirements-dev.txt
requirements-ml.txt
requirements.txt
setup.cfg
setup.py
.github/workflows/CI.template
.github/workflows/CI.yml
.github/workflows/publish.yml
sandbox/sandbox.ipynb
susml/__init__.py
susml/_version.py
susml.egg-info/PKG-INFO
susml.egg-info/SOURCES.txt
susml.egg-info/dependency_links.txt
susml.egg-info/requires.txt
susml.egg-info/top_level.txt
susml/torch/__init__.py
susml/torch/data.py
susml/torch/models.py
susml/torch/utils.py
tests/__init__.py
tests/torch/test_models.py
tests/torch/test_utils.py