Metadata-Version: 2.1
Name: susml
Version: 0.0.1
Summary: A ML toolkit with code bits useful for our day to day research
Home-page: https://github.com/sustainability-lab/SusML
Author: Nipun Batra
Author-email: nipun.batra@iitgn.ac.in
License: MIT
Requires-Python: >=3.9
Requires-Dist: numpy
Requires-Dist: pandas
Requires-Dist: matplotlib
Requires-Dist: xarray
Requires-Dist: tqdm
Requires-Dist: optree
